core_cdc/__init__.py
core_cdc/base.py
core_cdc/py.typed
core_cdc/processors/__init__.py
core_cdc/processors/base.py
core_cdc/processors/mssql.py
core_cdc/processors/oracle.py
core_cdc/processors/mongo/__init__.py
core_cdc/processors/mongo/mongo_stream.py
core_cdc/processors/mysql/__init__.py
core_cdc/processors/mysql/mysql_binlog.py
core_cdc/targets/__init__.py
core_cdc/targets/base.py
core_cdc/targets/mysql.py
core_cdc/targets/snowflake.py
core_cdc-2.0.1.dist-info/licenses/LICENSE
core_cdc-2.0.1.dist-info/METADATA
core_cdc-2.0.1.dist-info/WHEEL
core_cdc-2.0.1.dist-info/top_level.txt
core_cdc-2.0.1.dist-info/RECORD
