Metadata-Version: 2.4
Name: core-cdc
Version: 2.0.1
Summary: This library provides the mechanism to implement Change Data Capture (CDC) services...
Author-email: Alejandro Cora González <alek.cora.glez@gmail.com>
Maintainer: Alejandro Cora González
License-Expression: MIT
Project-URL: Homepage, https://gitlab.com/bytecode-solutions/core/core-cdc
Project-URL: Repository, https://gitlab.com/bytecode-solutions/core/core-cdc
Project-URL: Documentation, https://core-cdc.readthedocs.io/en/latest/
Project-URL: Issues, https://gitlab.com/bytecode-solutions/core/core-cdc/-/issues
Project-URL: Changelog, https://gitlab.com/bytecode-solutions/core/core-cdc/-/blob/master/CHANGELOG.md
Classifier: Intended Audience :: Developers
Classifier: Development Status :: 5 - Production/Stable
Classifier: Topic :: Software Development :: Libraries :: Python Modules
Classifier: Topic :: Utilities
Classifier: Programming Language :: Python :: 3
Classifier: Programming Language :: Python :: 3 :: Only
Classifier: Programming Language :: Python :: 3.9
Classifier: Programming Language :: Python :: 3.10
Classifier: Programming Language :: Python :: 3.11
Classifier: Programming Language :: Python :: 3.12
Classifier: Programming Language :: Python :: 3.13
Requires-Python: >=3.9
License-File: LICENSE
Requires-Dist: core-mixins>=2.2.4
Requires-Dist: core-tests>=2.0.3
Provides-Extra: all
Requires-Dist: core-db[all]>=3.0.1; extra == "all"
Requires-Dist: mysql-replication>=1.0.9; extra == "all"
Provides-Extra: dev
Requires-Dist: core-dev-tools>=1.0.1; extra == "dev"
Provides-Extra: mongo
Requires-Dist: core-db[mongo]>=3.0.1; extra == "mongo"
Provides-Extra: mysql
Requires-Dist: core-db[mysql]>=3.0.1; extra == "mysql"
Requires-Dist: mysql-replication>=1.0.9; extra == "mysql"
Provides-Extra: snowflake
Requires-Dist: core-db[snowflake]>=3.0.1; extra == "snowflake"
Dynamic: license-file
